{"status": "past", "rating": {"count": 8, "average": 4.880000114440918}, "utc_offset": -10800000, "event_url": "http://www.meetup.com/WordPressBeloHorizonte/events/117860502/", "group": {"who": "Amantes do WordPress", "name": "Belo Horizonte WordPress Group", "group_lat": -19.920000076293945, "created": 1367631417000, "join_mode": "open", "group_lon": -43.939998626708984, "urlname": "WordPressBeloHorizonte", "id": 8337282}, "description": "<p>Pessoal esta confirmado o Local. A Faculdade Delrey, que fica no bairro Floresta vai estar nos patrocinando com o local para nosso encontro no dia 25 de Maio das 10h as 12h.</p> <p>Endere\u00e7o:</p> <p>Rua Ub\u00e1, 396 \u2013 Floresta - Belo Horizonte/MG - Fone: (31)[masked]</p> <p><a href=\"http://www.faculdadesdelrey.com.br\"><a href=\"http://www.faculdadesdelrey.com.br\" class=\"linkified\">http://www.faculdadesdelrey.com.br</a></a></p> <p>Vamos tentar um patroc\u00ednio fixo com eles, para termos sempre um local para os encontros e vamos estar divulgando a Faculdade Delrey sempre em nosso eventos.</p> <p>Sobre o evento</p> <p>A id\u00e9ia central vai ser apresentar as novidades do WordPress 3.6, sua pr\u00f3xima vers\u00e3o ainda n\u00e3o lan\u00e7ada oficialmente, e tamb\u00e9m \u00e9 claro j\u00e1 come\u00e7ar a trocar id\u00e9ias e experi\u00eancias de uso do WordPress.</p>", "created": 1367782704000, "rsvp_limit": 30, "venue": {"city": "Belo Horizonte", "name": "Faculdade Delrey", "country": "br", "lon": -43.936634, "address_1": "Rua Ub\u00e1, 396 \u2013 Floresta - Belo Horizonte - MG", "repinned": true, "lat": -19.910284, "id": 13464942}, "updated": 1369680340000, "visibility": "public", "id": "117860502", "yes_rsvp_count": 30, "time": 1369485000000, "duration": 9000000, "waitlist_count": 0, "headcount": 0, "maybe_rsvp_count": 0, "how_to_find_us": "Faculdade Delrey", "name": "Primeiro encontro e comemora\u00e7\u00e3o aos 10 anos de WordPress (Vagas Esgotadas!)"}
{"status": "past", "rating": {"count": 2, "average": 5}, "utc_offset": -10800000, "event_url": "http://www.meetup.com/WordPressBeloHorizonte/events/121291472/", "group": {"who": "Amantes do WordPress", "name": "Belo Horizonte WordPress Group", "group_lat": -19.920000076293945, "created": 1367631417000, "join_mode": "open", "group_lon": -43.939998626708984, "urlname": "WordPressBeloHorizonte", "id": 8337282}, "description": "<p>Pessoal, agora \u00e9 a vez de mostrar que somos capazes de trazer um grande eventos pra BH. Durante todo o dia 27, ser\u00e1 usado a hashtag #wp10 e #wp10BR. Que tal usarmos tamb\u00e9m a #wp10BH e postar fotos desse evento, fotos relacionadas a WP, e tudo que tem direito. Vamos movimentar nosso Twitter, Instagram e tudo que tem direito para esse grande evento.</p> <p>\u00a0</p> <p>Aproveitando, mesmo que voc\u00ea n\u00e3o consiga fazer isso, confirme sua participa\u00e7\u00e3o nesse evento oficial.</p> <p><a href=\"http://www.meetup.com/WordPress/Belo-Horizonte-BR/\"><a href=\"http://www.meetup.com/WordPress/Belo-Horizonte-BR/\" class=\"linkified\">http://www.meetup.com/WordPress/Belo-Horizonte-BR/</a></a></p> <p>\u00a0</p> <p>Abra\u00e7o a todos e obrigado pelo apoio.</p>", "created": 1369576739000, "venue": {"city": "Belo Horizonte", "name": "Online", "country": "br", "lon": -43.938576, "address_1": "Twitter, Instagram", "repinned": false, "lat": -19.919067, "id": 13640742}, "updated": 1369664253000, "visibility": "public", "yes_rsvp_count": 13, "time": 1369652400000, "waitlist_count": 0, "headcount": 0, "maybe_rsvp_count": 0, "id": "121291472", "name": "#WP10 e #WP10BH"}
{"status": "past", "rating": {"count": 4, "average": 5}, "utc_offset": -10800000, "event_url": "http://www.meetup.com/WordPressBeloHorizonte/events/124578202/", "group": {"who": "Amantes do WordPress", "name": "Belo Horizonte WordPress Group", "group_lat": -19.920000076293945, "created": 1367631417000, "join_mode": "open", "group_lon": -43.939998626708984, "urlname": "WordPressBeloHorizonte", "id": 8337282}, "description": "<p>Nosso tema escolhido para nosso pr\u00f3ximo encontro foi:</p> <p><b>Boas pr\u00e1ticas de desenvolvimento de temas para WordPress</b></p> <p>Este tema vai envolver a apresenta\u00e7\u00e3o e discus\u00e3o de boas pr\u00e1ticas de desenvolvimento com WordPress, como por exemplo: organiza\u00e7\u00e3o da estrutura do tema, cuidados com os Loops, classes padr\u00f5es do WordPress entre outros.</p> <p>A princ\u00edpio eu, Mateus Neves, irei fazer apresenta\u00e7\u00e3o, mas estamos abertos a todos se algu\u00e9m quiser preparar algo em espec\u00edfico para apresentar na nossa discuss\u00e3o sobre este tema, seria muito bom.</p> <p>A programa\u00e7\u00e3o vai iniciar as 9h e terminar 12h do dia 22 de Junho, na Faculdade Del Rey.</p> <p>\u00a0</p>", "created": 1371180247000, "rsvp_limit": 80, "updated": 1373887634000, "visibility": "public", "yes_rsvp_count": 31, "time": 1371902400000, "duration": 10800000, "waitlist_count": 0, "headcount": 0, "maybe_rsvp_count": 0, "id": "124578202", "name": "Boas pr\u00e1ticas de desenvolvimento de temas para WordPress"}
{"status": "past", "rating": {"count": 8, "average": 4.75}, "utc_offset": -10800000, "event_url": "http://www.meetup.com/WordPressBeloHorizonte/events/129602552/", "group": {"who": "Amantes do WordPress", "name": "Belo Horizonte WordPress Group", "group_lat": -19.920000076293945, "created": 1367631417000, "join_mode": "open", "group_lon": -43.939998626708984, "urlname": "WordPressBeloHorizonte", "id": 8337282}, "description": "<p>Nesta apresenta\u00e7\u00e3o veremos uma s\u00e9rie de boas pr\u00e1ticas adotadas na constru\u00e7\u00e3o de um tema de alta performance.</p> <p>Ser\u00e3o apresentados alguns conceitos que nos motivam a construir sites mais velozes e v\u00e1rias ferramentas e t\u00e9cnicas</p> <p>que facilitam a produ\u00e7\u00e3o, organiza\u00e7\u00e3o e manuten\u00e7\u00e3o dos c\u00f3digo e arquivos utilizados no projeto.</p> <p>\u00a0</p> <p><b>Palestrante: Bruce Emmanuel<br/></b></p> <p>Bruce Emmanuel Sueira \u00e9 Bombeiro Militar e a 5 anos, trabalha dentro da institui\u00e7\u00e3o exclusivamente na \u00e1rea de tecnologia da informa\u00e7\u00e3o, onde teve a oportunidade de realizar v\u00e1rios cursos de capacita\u00e7\u00e3o e certifica\u00e7\u00e3o focados em todas as \u00e1reas do desenvolvimento web, ger\u00eancia de projetos e administra\u00e7\u00e3o de servidores Linux e Windows.</p> <p>Tem em seu curr\u00edculo portais, sistemas de ensino a dist\u00e2ncia e intranets de medicina e do governo do estado de Minas Gerais.</p> <p>Como consultor e programador trabalha com projetos de otimiza\u00e7\u00e3o e cria\u00e7\u00e3o de sites de alta performance.</p>", "created": 1373857918000, "rsvp_limit": 30, "venue": {"city": "Belo Horizonte", "name": "Faculdade Delrey", "country": "br", "lon": -43.936634, "address_1": "Rua Ub\u00e1, 396 \u2013 Floresta - Belo Horizonte - MG", "repinned": false, "lat": -19.910284, "id": 13464942}, "updated": 1375213068000, "visibility": "public", "yes_rsvp_count": 16, "time": 1374926400000, "duration": 10800000, "waitlist_count": 0, "headcount": 0, "maybe_rsvp_count": 0, "id": "129602552", "name": "Performance de front-end, preparando o terreno antes da integra\u00e7\u00e3o com Wordpress"}
{"status": "past", "rating": {"count": 8, "average": 4.25}, "utc_offset": -10800000, "event_url": "http://www.meetup.com/WordPressBeloHorizonte/events/132713972/", "group": {"who": "Amantes do WordPress", "name": "Belo Horizonte WordPress Group", "group_lat": -19.920000076293945, "created": 1367631417000, "join_mode": "open", "group_lon": -43.939998626708984, "urlname": "WordPressBeloHorizonte", "id": 8337282}, "description": "<p>Ol\u00e1 povo,</p> <p>Amanh\u00e3 acontece o FrontinBH, e acho bacana tentar juntar todos para participar juntos desse evento, j\u00e1 que tamb\u00e9m conta como algo voltado ao WordPress.</p> <p>Dessa vez eu juro que vou comparecer rs.</p> <p>\n\n\nAt\u00e9 amanh\u00e3.</p>", "created": 1375452004000, "venue": {"city": "Belo Horizonte", "name": "Teatro Ney Soares", "country": "br", "lon": -43.941528, "address_1": "Rua Diamantina, 463", "repinned": false, "lat": -19.90789, "id": 14894562}, "updated": 1375720783000, "visibility": "public", "yes_rsvp_count": 18, "time": 1375527600000, "waitlist_count": 0, "headcount": 30, "maybe_rsvp_count": 0, "id": "132713972", "name": "FrontinBH"}
{"status": "past", "rating": {"count": 1, "average": 5}, "utc_offset": -10800000, "event_url": "http://www.meetup.com/WordPressBeloHorizonte/events/133080472/", "group": {"who": "Amantes do WordPress", "name": "Belo Horizonte WordPress Group", "group_lat": -19.920000076293945, "created": 1367631417000, "join_mode": "open", "group_lon": -43.939998626708984, "urlname": "WordPressBeloHorizonte", "id": 8337282}, "description": "<p><a href=\"http://devday.devisland.com/\"><a href=\"http://devday.devisland.com/\" class=\"linkified\">http://devday.devisland.com/</a></a></p> <p>\n\n\n\nO DevDay \u00e9 um evento de desenvolvimento que acontece em BH anualmente. Esse ano ir\u00e3o apoiar a comunidade WordPress e WordPress BH.</p> <p>Estou tentando um desconto ou alguns para sorteio pra levar a comunidade.</p> <p>\u00c9 um \u00f3timo evento pra quem quer aperfei\u00e7oar o conhecimento, focado 100% em desenvolvimento.</p> <p>Para saber mais visite o site do evento:\u00a0<a href=\"http://devday.devisland.com/\"><a href=\"http://devday.devisland.com/\" class=\"linkified\">http://devday.devisland.com/</a></a>\u00a0</p> <p>Novidades vou colocando pra voc\u00eas.</p>", "created": 1375660931000, "venue": {"city": "Belo Horizonte", "name": "UNI-BH (campus Estoril)", "country": "br", "lon": -43.964981, "address_1": "Av. Prof. M\u00e1rio Werneck, 1685, Estoril", "repinned": false, "lat": -19.970528, "id": 14933232}, "updated": 1382290480000, "visibility": "public", "yes_rsvp_count": 15, "time": 1382180400000, "duration": 39600000, "waitlist_count": 0, "headcount": 0, "maybe_rsvp_count": 0, "id": "133080472", "name": "DEVDAY BH 2013"}
{"status": "past", "rating": {"count": 0, "average": 0}, "utc_offset": -7200000, "event_url": "http://www.meetup.com/WordPressBeloHorizonte/events/143819302/", "group": {"who": "Amantes do WordPress", "name": "Belo Horizonte WordPress Group", "group_lat": -19.920000076293945, "created": 1367631417000, "join_mode": "open", "group_lon": -43.939998626708984, "urlname": "WordPressBeloHorizonte", "id": 8337282}, "description": "<p>WordCamp \u00e9 o evento oficial do WordPress, focado tanto para iniciantes quanto para desenvolvedores.</p> <p>Em Novembro acontece em S\u00e3o Paulo, quem quiser j\u00e1 pode planejar a ida.</p> <p>\n\n\nSaiba mais em\u00a0<a href=\"http://2013.saopaulo.wordcamp.org/\"><a href=\"http://2013.saopaulo.wordcamp.org\" class=\"linkified\">http://2013.saopaulo.wordcamp.org</a></a></p>", "created": 1380898114000, "updated": 1385211883000, "visibility": "public", "yes_rsvp_count": 1, "time": 1385200800000, "waitlist_count": 0, "headcount": 0, "maybe_rsvp_count": 0, "id": "143819302", "name": "WordCamp S\u00e3o Paulo 2013"}
{"status": "past", "rating": {"count": 4, "average": 4.5}, "utc_offset": -10800000, "fee": {"description": "por pessoa", "required": "0", "accepts": "cash", "label": "Pre\u00e7o", "currency": "BRL", "amount": 35}, "group": {"who": "Amantes do WordPress", "name": "Belo Horizonte WordPress Group", "group_lat": -19.920000076293945, "created": 1367631417000, "join_mode": "open", "group_lon": -43.939998626708984, "urlname": "WordPressBeloHorizonte", "id": 8337282}, "description": "<p>O WordCamp \u00e9 uma confer\u00eancia sem fins lucrativos que busca criar e compartilhar conhecimento sobre o WordPress. \u00c9 um conjunto de palestras, debates e oficinas destinado tanto a desenvolvedores como a usu\u00e1rios. Originado nos Estados Unidos, o evento acontece em todo mundo e conta com o apoio da Funda\u00e7\u00e3o WordPress e da Automattic, detentora da marca WordPress. Em 2014, Belo Horizonte recebe o WordCamp pela primeira vez e se torna a 4\u00aa capital brasileira a sediar o evento.</p>", "created": 1394479255000, "venue": {"city": "Belo Horizonte", "name": "UNI-BH (campus Estoril)", "country": "br", "lon": -43.964981, "address_1": "Av. Prof. M\u00e1rio Werneck, 1685, Estoril", "repinned": false, "lat": -19.970528, "id": 14933232}, "updated": 1400709011000, "visibility": "public", "yes_rsvp_count": 25, "event_url": "http://www.meetup.com/WordPressBeloHorizonte/events/170526982/", "time": 1400324400000, "duration": 36000000, "waitlist_count": 0, "headcount": 0, "maybe_rsvp_count": 0, "id": "170526982", "name": "WordCamp Belo horizonte"}
{"status": "past", "rating": {"count": 0, "average": 0}, "utc_offset": -10800000, "event_url": "http://www.meetup.com/WordPressBeloHorizonte/events/184175592/", "group": {"who": "Amantes do WordPress", "name": "Belo Horizonte WordPress Group", "group_lat": -19.920000076293945, "created": 1367631417000, "join_mode": "open", "group_lon": -43.939998626708984, "urlname": "WordPressBeloHorizonte", "id": 8337282}, "description": "<p>O\u00a0Dev in Company BH\u00a0surge como um meio de fomentar o mercado de desenvolvimento em\u00a0Belo Horizonte, tendo como foco principal criar uma alta intera\u00e7\u00e3o entre profissionais e empresas locais, para que estes tragam consigo talentos e projetos interessantes de forma descontra\u00edda e rica em conhecimento t\u00e9cnico, al\u00e9m de proporcionar um \u00f3timo network para todos os presentes.</p>", "created": 1400614007000, "venue": {"city": "Belo Horizonte", "name": "SEED Minas Gerais", "country": "br", "lon": -43.94426, "address_1": "Rua Curitiba, 1957, Lourdes", "repinned": false, "lat": -19.930264, "id": 20234032}, "updated": 1401544950000, "visibility": "public", "yes_rsvp_count": 7, "time": 1401534000000, "waitlist_count": 0, "headcount": 0, "maybe_rsvp_count": 0, "id": "184175592", "name": "Dev in Company"}
{"status": "past", "rating": {"count": 1, "average": 5}, "utc_offset": -10800000, "fee": {"description": "por pessoa", "required": "0", "accepts": "cash", "label": "Pre\u00e7o", "currency": "BRL", "amount": 70}, "group": {"who": "Amantes do WordPress", "name": "Belo Horizonte WordPress Group", "group_lat": -19.920000076293945, "created": 1367631417000, "join_mode": "open", "group_lon": -43.939998626708984, "urlname": "WordPressBeloHorizonte", "id": 8337282}, "description": "<p>Podemos nos encontrar mais uma vez, dessa vez no Frontin-BH.</p>", "created": 1403206579000, "venue": {"city": "Belo Horizonte", "name": "Teatro Ney Soares", "country": "br", "lon": -43.941528, "address_1": "Rua Diamantina, 463", "repinned": false, "lat": -19.90789, "id": 14894562}, "updated": 1406611786000, "visibility": "public", "yes_rsvp_count": 16, "event_url": "http://www.meetup.com/WordPressBeloHorizonte/events/190067942/", "time": 1406372400000, "waitlist_count": 0, "headcount": 0, "maybe_rsvp_count": 0, "id": "190067942", "name": "FrontinBH"}
{"status": "past", "rating": {"count": 1, "average": 5}, "utc_offset": -10800000, "event_url": "http://www.meetup.com/WordPressBeloHorizonte/events/200731652/", "group": {"who": "Amantes do WordPress", "name": "Belo Horizonte WordPress Group", "group_lat": -19.920000076293945, "created": 1367631417000, "join_mode": "open", "group_lon": -43.939998626708984, "urlname": "WordPressBeloHorizonte", "id": 8337282}, "description": "<p>Esse ser\u00e1 um Meetup para definir, assuntos, locais, datas das pr\u00f3ximas palestras e Meetups da comunidade BH.</p> <p>Participe e ajude a decidir mais sobre a comunidade.</p> <p>O evento ser\u00e1 em um Bar, por ser neutro e central, mas n\u00e3o necessariamente haver\u00e1 ou \u00e9 obrigado consumo de bebida alco\u00f3licas para quem n\u00e3o gosta.</p> <p>Voc\u00ea realmente ir\u00e1? S\u00f3 confirme presen\u00e7a se realmente for comparecer, pois como \u00e9 um bar, as mesas ser\u00e3o reservadas de acordo com essas reservas.</p> <p>\n\n\n\n<a href=\"https://www.facebook.com/BarIdealBH\"><a href=\"https://www.facebook.com/BarIdealBH\" class=\"linkified\">https://www.facebook.com/BarIdealBH</a></a></p> <p><br/><a href=\"http://www.barideal.com.br/\"><a href=\"http://www.barideal.com.br\" class=\"linkified\">http://www.barideal.com.br</a></a></p>", "created": 1407949372000, "rsvp_limit": 20, "venue": {"city": "Belo Horizonte", "name": "Bar Ideal", "country": "br", "lon": -43.937843, "address_1": "Rua Sergipe, 1187 - Savassi", "repinned": false, "lat": -19.936911, "id": 17536242}, "updated": 1408501396000, "visibility": "public", "yes_rsvp_count": 8, "time": 1408489200000, "waitlist_count": 0, "headcount": 8, "maybe_rsvp_count": 0, "id": "200731652", "name": "Meetup para Organiza\u00e7\u00e3o e volta da Comunidade WordPress BH"}
{"status": "past", "rating": {"count": 1, "average": 5}, "utc_offset": -10800000, "event_url": "http://www.meetup.com/WordPressBeloHorizonte/events/201992432/", "group": {"who": "Amantes do WordPress", "name": "Belo Horizonte WordPress Group", "group_lat": -19.920000076293945, "created": 1367631417000, "join_mode": "open", "group_lon": -43.939998626708984, "urlname": "WordPressBeloHorizonte", "id": 8337282}, "description": "<p>Confirme presen\u00e7a em:<br/><a href=\"http://www.eventick.com.br/meetupwpbh092014\" class=\"linkified\">http://www.eventick.com.br/meetupwpbh092014</a></p> <p>S\u00f3 ser\u00e3o v\u00e1lidos presen\u00e7a com ingressos do Eventick impresso.<br/>#######</p> <p>O WordPress BH Group ter\u00e1 um foco em seus encontros, seguindo uma linha de racioc\u00ednio.</p> <p>Nosso primeiro encontro \u00e9, Conhecendo o WordPress. Palestra focada para iniciantes e produtores de conte\u00fado.</p> <p>Conte\u00fado:</p> <p>Conhecendo o WordPress;</p> <p>N\u00fameros;</p> <p>Pastas e Arquivos;</p> <p>Como instalar o WordPress;</p> <p>Dicas e como Usar o Painel;</p> <p>Com esse material ser\u00e1 poss\u00edvel conhecer o b\u00e1sico para avan\u00e7ar nas pr\u00f3ximas edi\u00e7\u00f5es dos Meetups, todas com assunto seguinte ao Meetup anterior.</p> <p>Evento gratuito, sem Coffee Break e Almo\u00e7o.</p> <p>Somente confirme presen\u00e7a se realmente for, para n\u00e3o tirar a chance de quem deseja comparecer.</p> <p>Vagas limitadas \u00e0 50 lugares.</p> <p>Curta: <a href=\"https://www.facebook.com/BHWPGroup\" class=\"linkified\">https://www.facebook.com/BHWPGroup</a></p>", "created": 1408499623000, "rsvp_limit": 50, "updated": 1410022609000, "visibility": "public", "yes_rsvp_count": 20, "time": 1410004800000, "duration": 12600000, "waitlist_count": 0, "headcount": 0, "maybe_rsvp_count": 0, "id": "201992432", "name": "Conhecendo o WordPress"}
{"status": "past", "rating": {"count": 0, "average": 0}, "utc_offset": -10800000, "event_url": "http://www.meetup.com/WordPressBeloHorizonte/events/206169942/", "group": {"who": "Amantes do WordPress", "name": "Belo Horizonte WordPress Group", "group_lat": -19.920000076293945, "created": 1367631417000, "join_mode": "open", "group_lon": -43.939998626708984, "urlname": "WordPressBeloHorizonte", "id": 8337282}, "description": "<p>Saiba as novidades do 4.0 em um evento online com membros do grupo do Facebook. O link ser\u00e1 disponibilizado minutos antes em:</p> <p><a href=\"http://migre.me/lxweW\" class=\"linkified\">http://migre.me/lxweW</a></p>", "created": 1410275187000, "venue": {"city": "Belo Horizonte", "name": "Hangout", "country": "br", "lon": 0, "address_1": "youtube.com", "repinned": false, "lat": 0, "id": 22279702}, "updated": 1410405386000, "visibility": "public", "id": "206169942", "yes_rsvp_count": 9, "time": 1410391800000, "waitlist_count": 0, "headcount": 0, "maybe_rsvp_count": 0, "how_to_find_us": "O link ser\u00e1 disponibilizado minutos antes em http://migre.me/lxweW", "name": "Novidades Do WordPress 4.0"}
{"status": "past", "rating": {"count": 1, "average": 5}, "utc_offset": -7200000, "event_url": "http://www.meetup.com/WordPressBeloHorizonte/events/215267982/", "group": {"who": "Amantes do WordPress", "name": "Belo Horizonte WordPress Group", "group_lat": -19.920000076293945, "created": 1367631417000, "join_mode": "open", "group_lon": -43.939998626708984, "urlname": "WordPressBeloHorizonte", "id": 8337282}, "description": "<p>Nesse hangout vamos conversar um pouco sobre o que foi falado em diversos WordCamps nas \u00faltimas edi\u00e7\u00f5es. Como fazer parte da Comunidade WordPress, como posso ajudar.</p> <p>Esse hangout \u00e9 uma previa do que acontecer\u00e1 sabado na UniBH.</p> <p>O Link para a transmiss\u00e3o ser\u00e1 divulgado horas antes em <a href=\"https://www.facebook.com/events/1500086656922724/\" class=\"linkified\">https://www.facebook.com/events/1500086656922724/</a></p>", "created": 1414104583000, "venue": {"city": "Belo Horizonte", "name": "Hangout", "country": "br", "lon": 0, "address_1": "youtube.com", "repinned": false, "lat": 0, "id": 22279702}, "updated": 1414553928000, "visibility": "public", "yes_rsvp_count": 15, "time": 1414539000000, "waitlist_count": 0, "headcount": 0, "maybe_rsvp_count": 0, "id": "215267982", "name": "Hangout: Comunidade WordPress, como participar."}
{"status": "past", "rating": {"count": 2, "average": 4.5}, "utc_offset": -7200000, "event_url": "http://www.meetup.com/WordPressBeloHorizonte/events/214757842/", "group": {"who": "Amantes do WordPress", "name": "Belo Horizonte WordPress Group", "group_lat": -19.920000076293945, "created": 1367631417000, "join_mode": "open", "group_lon": -43.939998626708984, "urlname": "WordPressBeloHorizonte", "id": 8337282}, "description": "<p>::ATEN\u00c7\u00c3O::</p> <p>S\u00f3 ser\u00e3o aceitos presen\u00e7as confirmadas no site:</p> <p><a href=\"http://even.tc/meetupbh112014\" class=\"linkified\">http://even.tc/meetupbh112014</a></p> <p><br/>O objetivo da palestra \u00e9 entender como o WordPress foi projetado e constru\u00eddo, analisando seus fundamentos, para que possamos ampliar o seu uso, aprender a desenvolver e customiz\u00e1-lo corretamente.</p>", "created": 1413901097000, "venue": {"city": "Belo Horizonte", "name": "UNI-BH (Campus Cristiano Machado/Minas Shopping/Hipermercado Extra)", "country": "br", "lon": -43.927402, "address_1": "Avenida Cristiano Machado, 4000, Cidade Nova", "repinned": false, "lat": -19.874315, "id": 21895612}, "updated": 1414959035000, "visibility": "public", "yes_rsvp_count": 27, "time": 1414839600000, "duration": 10800000, "waitlist_count": 0, "headcount": 0, "maybe_rsvp_count": 0, "id": "214757842", "name": "Fundamentos do WordPress: desconstruindo para conhecer"}
{"status": "past", "rating": {"count": 4, "average": 4.75}, "utc_offset": -10800000, "event_url": "http://www.meetup.com/WordPressBeloHorizonte/events/221867884/", "group": {"who": "Amantes do WordPress", "name": "Belo Horizonte WordPress Group", "group_lat": -19.920000076293945, "created": 1367631417000, "join_mode": "open", "group_lon": -43.939998626708984, "urlname": "WordPressBeloHorizonte", "id": 8337282}, "description": "<p>ATEN\u00c7\u00c3O: S\u00d3 SER\u00c1 CONFIRMADO SUA PRESEN\u00c7A AP\u00d3S A COMPRA EM <a href=\"http://www.eventick.com.br/bhwordpressabril2015\" class=\"linkified\">http://www.eventick.com.br/bhwordpressabril2015</a></p> <p>O VALOR DESSE INGRESSO SER\u00c1 REVERTIDO EM UM CAF\u00c9 DA MANH\u00c3</p> <p><br/>\u00daltimo Meetup antes do WordCamp BH. Duas palestras em uma.</p> <p>Primeiro voc\u00ea vai aprender a Criar temas do zero para WordPress. Dicas, novidades e utilidades na hora de criar seu tema.<br/>Com Davi Alves</p> <p>Depois o Marketing de conte\u00fado toma conta da sala, aprendendo dicas de como ter um conte\u00fado relevante.<br/>Com Gabi Denizot.</p>", "created": 1429123144000, "venue": {"city": "Belo Horizonte", "name": "UNI-BH (campus Estoril)", "country": "br", "lon": -43.964981, "address_1": "Av. Prof. M\u00e1rio Werneck, 1685, Estoril", "repinned": false, "lat": -19.970528, "id": 14933232}, "updated": 1430077395000, "visibility": "public", "yes_rsvp_count": 20, "time": 1429963200000, "waitlist_count": 0, "headcount": 16, "maybe_rsvp_count": 0, "id": "221867884", "name": "Criando seu tema para WordPress e Marketing de Conte\u00fado"}
{"status": "past", "rating": {"count": 6, "average": 5}, "utc_offset": -10800000, "fee": {"description": "por pessoa", "required": "0", "accepts": "cash", "label": "Pre\u00e7o", "currency": "BRL", "amount": 45}, "group": {"who": "Amantes do WordPress", "name": "Belo Horizonte WordPress Group", "group_lat": -19.920000076293945, "created": 1367631417000, "join_mode": "open", "group_lon": -43.939998626708984, "urlname": "WordPressBeloHorizonte", "id": 8337282}, "description": "<p><a href=\"http://belohorizonte.wordcamp.org/2015/\" class=\"linkified\">http://belohorizonte.wordcamp.org/2015/</a></p> <p><br/>O<a href=\"http://central.wordcamp.org/\">\u00a0WordCamp</a>\u00a0\u00e9 uma confer\u00eancia sem fins lucrativos, que busca criar e compartilhar conhecimento sobre WordPress. O evento conta com um conjunto de palestras, debates e oficinas destinadas \u00e0 desenvolvedores e usu\u00e1rios.</p> <p>Originado nos Estados unidos, o evento acontece no mundo todo, e com com o apoio da\u00a0<a href=\"http://wordpressfoundation.org/\">Funda\u00e7\u00e3o WordPress</a>\u00a0e da<a href=\"http://automattic.com/\">\u00a0Automattic</a>, detentora da marca\u00a0<a href=\"http://wordpress.org/\">WordPress</a>.</p> <p>Belo Horizonte \u00e9 a 4\u00b0 capital brasileira a sediar o evento.</p> <p><b>O P\u00daBLICO</b></p> <p>O WordCamp busca reunir desenvolvedores, designers, publicit\u00e1rios, jornalistas, blogueiros e usu\u00e1rios casuais para debater os avan\u00e7os, usabilidade, ferramentas, plugins e o c\u00f3digo do WordPress, ampliando a comunidade de usu\u00e1rios, profissionais e entusiastas.</p> <p><b>HIST\u00d3RIA</b></p> <p>O primeiro WordCamp acontecem em julho de 2006 em S\u00e3o Francisco. Organizado por Matt Mullenweg, criador do WordPress, conseguiu em apenas tr\u00eas semanas reunir mais de 300 participantes, tornando-se um sucesso imediato. A sua primeira edi\u00e7\u00e3o internacional conhecida aconteceu em Israel no dia 25 de outubro de 2007. Desde ent\u00e3o, o WordCamp se espalhou pelas principais cidades do mundo, como Paris, Mil\u00e3o, T\u00f3quio, Melbourne, Sydney, Birmingham, Hamburgo e Vancouver. Em 2009, para alegria de uma das maiores comunidades do planeta, foi realizado o primeiro WordCamp Brasil, em S\u00e3o Paulo.</p> <p>Com o primeiro evento em SP, a comunidade come\u00e7ou a se organizar e realizar evento em outras cidades. Porto Alegre, Curitiba e Belo Horizonte come\u00e7aram a articular meetups para discutir a viabilidade de novos WordCamps.</p> <p>Em outubro de 2010 o evento foi realizado em Curitiba, contanto com cerca de 300 participantes nos dois dias de evento.</p> <p>Em 2013, Belo Horizonte foi aprovada pela funda\u00e7\u00e3o WordPress como cidade sede. Com uma equipe organizadora empolgada, liderada por Val\u00e9rio Souza \u2013 experiente desenvolvedor da plataforma \u2013 o evento aconteceu no dia\u00a017 de maio de 2014, com cerca de 300 pessoas.</p>", "created": 1425775954000, "venue": {"city": "Belo Horizonte", "name": "Teatro Ney Soares", "country": "br", "lon": -43.941528, "address_1": "Rua Diamantina, 463", "repinned": false, "lat": -19.90789, "id": 14894562}, "updated": 1434479102000, "visibility": "public", "yes_rsvp_count": 43, "event_url": "http://www.meetup.com/WordPressBeloHorizonte/events/220998083/", "time": 1434193200000, "duration": 36000000, "waitlist_count": 0, "headcount": 0, "maybe_rsvp_count": 0, "id": "220998083", "name": "WordCamp Belo Horizonte 2015"}
